metadata_api/__init__.py
metadata_api/metadata_api.py
metadata_api/metadata_api_api.py
metadata_api/apis/__init__.py
metadata_api/apis/dark_run_api.py
metadata_api/apis/data_file_api.py
metadata_api/apis/data_group_api.py
metadata_api/apis/data_group_repository_api.py
metadata_api/apis/data_group_type_api.py
metadata_api/apis/data_source_group_api.py
metadata_api/apis/data_source_group_version_api.py
metadata_api/apis/data_type_api.py
metadata_api/apis/experiment_api.py
metadata_api/apis/experiment_type_api.py
metadata_api/apis/instrument_api.py
metadata_api/apis/parameter_api.py
metadata_api/apis/parameter_type_api.py
metadata_api/apis/proposal_api.py
metadata_api/apis/proposal_technique_api.py
metadata_api/apis/report_api.py
metadata_api/apis/repostory_api.py
metadata_api/apis/run_api.py
metadata_api/apis/sample_api.py
metadata_api/apis/technique_api.py
metadata_api/apis/unit_api.py
metadata_api/apis/user_api.py
metadata_api/common/__init__.py
metadata_api/common/base.py
metadata_api/common/config.py
metadata_api/common/util.py
metadata_api/modules/__init__.py
metadata_api/modules/dark_run.py
metadata_api/modules/data_file.py
metadata_api/modules/data_group.py
metadata_api/modules/data_group_repository.py
metadata_api/modules/data_group_type.py
metadata_api/modules/data_source_group.py
metadata_api/modules/data_source_group_version.py
metadata_api/modules/data_type.py
metadata_api/modules/experiment.py
metadata_api/modules/experiment_type.py
metadata_api/modules/instrument.py
metadata_api/modules/parameter.py
metadata_api/modules/parameter_type.py
metadata_api/modules/proposal.py
metadata_api/modules/proposal_technique.py
metadata_api/modules/report.py
metadata_api/modules/repository.py
metadata_api/modules/run.py
metadata_api/modules/sample.py
metadata_api/modules/technique.py
metadata_api/modules/user.py
metadata_api/tests/__init__.py
metadata_api/tests/metadata_api_connection_test.py
metadata_api/tests/metadata_api_test.py
metadata_api/tests/apis/__init__.py
metadata_api-4.1.0.dist-info/licenses/AUTHORS.rst
metadata_api-4.1.0.dist-info/licenses/LICENSE
metadata_api-4.1.0.dist-info/METADATA
metadata_api-4.1.0.dist-info/WHEEL
metadata_api-4.1.0.dist-info/top_level.txt
metadata_api-4.1.0.dist-info/RECORD
